itk/GenericLabelInterpolatorPython.py
itk/_GenericLabelInterpolatorPython.pyd
itk/__init_genericlabelinterpolator__.py
itk/itkLabelImageGenericInterpolateImageFunctionPython.py
itk/Configuration/GenericLabelInterpolatorConfig.py
itk/Configuration/GenericLabelInterpolator_snake_case.py
itk_genericlabelinterpolator-1.3.0.dist-info/licenses/LICENSE
itk_genericlabelinterpolator.libs/msvcp140.dll
itk_genericlabelinterpolator-1.3.0.dist-info/DELVEWHEEL
itk_genericlabelinterpolator-1.3.0.dist-info/METADATA
itk_genericlabelinterpolator-1.3.0.dist-info/WHEEL
itk_genericlabelinterpolator-1.3.0.dist-info/RECORD
