Metadata-Version: 2.1
Name: itk-genericlabelinterpolator
Version: 1.3.0
Summary: ITK classes for generic interpolation of label images.
Keywords: itk,InsightToolkit,Label-images,Interpolation
Author-Email: =?utf-8?q?Jo=C3=ABl_Schaerer?= <joelthelion@laposte.net>
License: 
Classifier: Development Status :: 4 - Beta
Classifier: Intended Audience :: Developers
Classifier: Intended Audience :: Education
Classifier: Intended Audience :: Healthcare Industry
Classifier: Intended Audience :: Science/Research
Classifier: License :: OSI Approved :: Apache Software License
Classifier: Operating System :: Android
Classifier: Operating System :: MacOS
Classifier: Operating System :: Microsoft :: Windows
Classifier: Operating System :: POSIX
Classifier: Operating System :: Unix
Classifier: Programming Language :: C++
Classifier: Programming Language :: Python
Classifier: Topic :: Scientific/Engineering
Classifier: Topic :: Scientific/Engineering :: Information Analysis
Classifier: Topic :: Scientific/Engineering :: Medical Science Apps.
Classifier: Topic :: Software Development :: Libraries
Project-URL: Download, https://github.com/InsightSoftwareConsortium/ITKGenericLabelInterpolator
Project-URL: Homepage, https://github.com/InsightSoftwareConsortium/ITKGenericLabelInterpolator
Requires-Python: >=3.9
Requires-Dist: itk==5.4.*
